an_dtesetupmanager/__init__.py
an_dtesetupmanager/dtesetupmanager.py
an_dtesetupmanager-0.1.2.dist-info/LICENSE
an_dtesetupmanager-0.1.2.dist-info/METADATA
an_dtesetupmanager-0.1.2.dist-info/WHEEL
an_dtesetupmanager-0.1.2.dist-info/top_level.txt
an_dtesetupmanager-0.1.2.dist-info/RECORD
