Metadata-Version: 2.2
Name: an_dtesetupmanager
Version: 0.1.2
Summary: A package for an_dtesetupmanager.
Home-page: https://github.com/Atsushi888/Atsushi888
Author: Atsushi888
Author-email: Atsushi888 <vtgrotxu@gmail.com>
Project-URL: Homepage, https://github.com/Atsushi888/an_dtesetupmanager
Project-URL: Repository, https://github.com/Atsushi888/an_dtesetupmanager
Requires-Python: >=3.6
License-File: LICENSE
Requires-Dist: an_DebugHelper
Requires-Dist: an_EnvManager
Requires-Dist: an_CudaUtility
Dynamic: author
Dynamic: home-page
Dynamic: requires-python
